aces/__init__.py
aces/askapdata/CommonTypes.ice
aces/askapdata/DataServiceExceptions.ice
aces/askapdata/IService.ice
aces/askapdata/SBTemplateService.ice
aces/askapdata/SchedulingBlockService.ice
aces/askapdata/__init__.py
aces/askapdata/schedblock.py
aces/beamset/__init__.py
aces/beamset/airyfitter.py
aces/beamset/beam_summary.py
aces/beamset/beambase.py
aces/beamset/beamfactory.py
aces/beamset/beammap.py
aces/beamset/beammeasure.py
aces/beamset/beamset.py
aces/beamset/contourellipse.py
aces/beamset/gaussfitter.py
aces/beamset/mapset.py
aces/beamset/model.py
aces/beamset/modelset.py
aces/beamset/sefdset.py
aces/beamset/surfaceairy.py
aces/beamset/surfacegaussian.py
aces/cleanlog/__init__.py
aces/cleanlog/clean_parser.py
aces/clink/__init__.py
aces/clink/clink.py
aces/clink/tasks.py
aces/cluster_configs/__init__.py
aces/cluster_configs/clusters.py
aces/cluster_configs/environment.py
aces/cluster_configs/galaxy_holo.yaml
aces/cluster_configs/galaxy_large.yaml
aces/cluster_configs/galaxy_small.yaml
aces/cluster_configs/setonix.yaml
aces/data/__init__.py
aces/data/antenna-positions.txt
aces/data/footprints/__init__.py
aces/data/footprints/askap/__init__.py
aces/data/footprints/askap/boresight.parset
aces/data/footprints/askap/boresight_2.parset
aces/data/footprints/askap/central_ports.parset
aces/data/footprints/askap/closepack30.parset
aces/data/footprints/askap/closepack36.parset
aces/data/footprints/askap/hexagon36.parset
aces/data/footprints/askap/offset.parset
aces/data/footprints/askap/rect_2x3.parset
aces/data/footprints/askap/rectangle_6x6.parset
aces/data/footprints/askap/square_3x3.parset
aces/data/footprints/askap/square_6x6.parset
aces/data/footprints/askap/square_6x6_odd.parset
aces/data/footprints/askap_commissioning/__init__.py
aces/data/footprints/askap_commissioning/boresight.parset
aces/data/footprints/askap_commissioning/closepack36.parset
aces/data/footprints/askap_commissioning/square_6x6.parset
aces/data/footprints/effelsberg/__init__.py
aces_apps-1.5.4.dist-info/LICENSE
aces_apps-1.5.4.dist-info/WHEEL
aces_apps-1.5.4.dist-info/entry_points.txt
aces_apps-1.5.4.dist-info/METADATA
aces_apps-1.5.4.dist-info/RECORD
