Metadata-Version: 2.1
Name: aces-apps
Version: 1.5.4
Summary: A collection of utilities developed out of the ACES working group to support the processing of ASKAP data.
License: GPL
Author: David McConnell
Author-email: David.McConnell@csiro.au
Requires-Python: >=3.9,<4.0
Classifier: License :: Other/Proprietary License
Classifier: Programming Language :: Python :: 3
Classifier: Programming Language :: Python :: 3.9
Classifier: Programming Language :: Python :: 3.10
Classifier: Programming Language :: Python :: 3.11
Provides-Extra: docs
Requires-Dist: Cython (>=0.29.32,<0.30.0)
Requires-Dist: astropy (>=5.1,<6.0)
Requires-Dist: bokeh (>=2.4.3,<3.0.0)
Requires-Dist: clink (>=0.33.0,<0.34.0)
Requires-Dist: dask (>=2022.10.0,<2023.0.0)
Requires-Dist: dask-jobqueue (>=0.8.1,<0.9.0)
Requires-Dist: dask-mpi (>=2022.4.0,<2023.0.0)
Requires-Dist: distributed (>=2022.10.0,<2023.0.0)
Requires-Dist: ephem (>=4.1.3,<5.0.0)
Requires-Dist: graphviz (>=0.20.1,<0.21.0)
Requires-Dist: h5py (>=3.7.0,<4.0.0)
Requires-Dist: jupyter (>=1.0.0,<2.0.0)
Requires-Dist: lxml (>=4.9.1,<5.0.0)
Requires-Dist: matplotlib (>=3.6.1,<4.0.0)
Requires-Dist: mpi4py (>=3.1.3,<4.0.0)
Requires-Dist: multiprocessing-logging (>=0.3.3,<0.4.0)
Requires-Dist: nbdime (>=3.1.1,<4.0.0)
Requires-Dist: nose (>=1.3.7,<2.0.0)
Requires-Dist: numpy (>=1.23.4,<2.0.0)
Requires-Dist: prefect (>=2.6.4,<3.0.0)
Requires-Dist: prefect-dask (>=0.2.1,<0.3.0)
Requires-Dist: pytest (>=7.2.1,<8.0.0)
Requires-Dist: python-casacore (==3.5.00)
Requires-Dist: pytz (>=2022.4,<2023.0)
Requires-Dist: pyyaml (>=6.0,<7.0)
Requires-Dist: requests (>=2.28.1,<3.0.0)
Requires-Dist: scipy (>=1.9.2,<2.0.0)
Requires-Dist: seaborn (>=0.12.0,<0.13.0)
Requires-Dist: tqdm (>=4.64.1,<5.0.0)
Requires-Dist: zeroc-ice (>=3.7.8,<4.0.0)
